xosgenx
