Metadata-Version: 1.1
Name: xosgenx
Version: 3.1.0
Summary: XOS Generative Toolchain
Home-page: https://gerrit.opencord.org/gitweb?p=xos.git
Author: Sapan Bhatia, Matteo Scandolo
Author-email: cord-dev@opencord.org
License: Apache v2
Platform: UNKNOWN
Classifier: License :: OSI Approved :: Apache Software License
